{
"meta":{"test_sets":[],"test_metrics":[],"learn_metrics":[{"best_value":"Min","name":"Logloss"}],"launch_mode":"Train","parameters":"","iteration_count":350,"learn_sets":["learn"],"name":"experiment"},
"iterations":[
{"learn":[0.681114147],"iteration":0,"passed_time":0.001660356279,"remaining_time":0.5794643412},
{"learn":[0.6693438458],"iteration":1,"passed_time":0.003275244946,"remaining_time":0.5698926206},
{"learn":[0.6587094094],"iteration":2,"passed_time":0.004794557344,"remaining_time":0.5545704662},
{"learn":[0.650727411],"iteration":3,"passed_time":0.006261160558,"remaining_time":0.5415903883},
{"learn":[0.6413563549],"iteration":4,"passed_time":0.007713704044,"remaining_time":0.532245579},
{"learn":[0.6315525799],"iteration":5,"passed_time":0.009199256786,"remaining_time":0.5274240558},
{"learn":[0.6217575315],"iteration":6,"passed_time":0.01065133588,"remaining_time":0.521915458},
{"learn":[0.6125057922],"iteration":7,"passed_time":0.01269233584,"remaining_time":0.5425973573},
{"learn":[0.6038822414],"iteration":8,"passed_time":0.01439932693,"remaining_time":0.545574498},
{"learn":[0.5958502253],"iteration":9,"passed_time":0.01600982289,"remaining_time":0.5443339781},
{"learn":[0.588202201],"iteration":10,"passed_time":0.01763739383,"remaining_time":0.5435524098},
{"learn":[0.5825922172],"iteration":11,"passed_time":0.01927486895,"remaining_time":0.5429088088},
{"learn":[0.5748842577],"iteration":12,"passed_time":0.02075452115,"remaining_time":0.5380210484},
{"learn":[0.568213879],"iteration":13,"passed_time":0.02219126281,"remaining_time":0.5325903075},
{"learn":[0.560842485],"iteration":14,"passed_time":0.02368879089,"remaining_time":0.5290496632},
{"learn":[0.5562919637],"iteration":15,"passed_time":0.02518300736,"remaining_time":0.5256952786},
{"learn":[0.5497737993],"iteration":16,"passed_time":0.02695252282,"remaining_time":0.5279523589},
{"learn":[0.5454817328],"iteration":17,"passed_time":0.02872056274,"remaining_time":0.5297348239},
{"learn":[0.5399227259],"iteration":18,"passed_time":0.03017297336,"remaining_time":0.525644957},
{"learn":[0.5347702843],"iteration":19,"passed_time":0.03162796051,"remaining_time":0.5218613484},
{"learn":[0.5287461181],"iteration":20,"passed_time":0.03310339011,"remaining_time":0.5186197785},
{"learn":[0.5229372996],"iteration":21,"passed_time":0.03464752361,"remaining_time":0.5165630793},
{"learn":[0.5182809612],"iteration":22,"passed_time":0.03613542481,"remaining_time":0.5137514745},
{"learn":[0.513582391],"iteration":23,"passed_time":0.0376354905,"remaining_time":0.5112154127},
{"learn":[0.5106835645],"iteration":24,"passed_time":0.03911087375,"remaining_time":0.5084413588},
{"learn":[0.5060922118],"iteration":25,"passed_time":0.0405972307,"remaining_time":0.5059039518},
{"learn":[0.5024524942],"iteration":26,"passed_time":0.04203725789,"remaining_time":0.5028901592},
{"learn":[0.4975079645],"iteration":27,"passed_time":0.04350787509,"remaining_time":0.5003405635},
{"learn":[0.4934315019],"iteration":28,"passed_time":0.0455732984,"remaining_time":0.5044492685},
{"learn":[0.489478549],"iteration":29,"passed_time":0.04707975469,"remaining_time":0.50218405},
{"learn":[0.4866145358],"iteration":30,"passed_time":0.04852818857,"remaining_time":0.4993707146},
{"learn":[0.4850579718],"iteration":31,"passed_time":0.04970534076,"remaining_time":0.4939468238},
{"learn":[0.4821279292],"iteration":32,"passed_time":0.05131625683,"remaining_time":0.4929470732},
{"learn":[0.4785735687],"iteration":33,"passed_time":0.05290413198,"remaining_time":0.4916972266},
{"learn":[0.4754039632],"iteration":34,"passed_time":0.05437383405,"remaining_time":0.4893645065},
{"learn":[0.4725043543],"iteration":35,"passed_time":0.05575360461,"remaining_time":0.4862953291},
{"learn":[0.469762267],"iteration":36,"passed_time":0.05726717375,"remaining_time":0.4844493347},
{"learn":[0.4663928215],"iteration":37,"passed_time":0.05882101855,"remaining_time":0.4829515207},
{"learn":[0.4643515899],"iteration":38,"passed_time":0.06049962901,"remaining_time":0.4824457595},
{"learn":[0.4630956513],"iteration":39,"passed_time":0.06176742173,"remaining_time":0.4786975184},
{"learn":[0.4605513221],"iteration":40,"passed_time":0.06329533577,"remaining_time":0.4770307013},
{"learn":[0.4582935947],"iteration":41,"passed_time":0.0647811501,"remaining_time":0.4750617674},
{"learn":[0.4558039881],"iteration":42,"passed_time":0.06633925723,"remaining_time":0.4736314412},
{"learn":[0.453817101],"iteration":43,"passed_time":0.06774786412,"remaining_time":0.4711556004},
{"learn":[0.4512817519],"iteration":44,"passed_time":0.06925644495,"remaining_time":0.4694047935},
{"learn":[0.449132503],"iteration":45,"passed_time":0.0707565781,"remaining_time":0.4676086901},
{"learn":[0.4474277945],"iteration":46,"passed_time":0.07224186181,"remaining_time":0.4657294495},
{"learn":[0.4452154055],"iteration":47,"passed_time":0.07369067069,"remaining_time":0.4636371364},
{"learn":[0.4442536186],"iteration":48,"passed_time":0.0755443562,"remaining_time":0.4640581881},
{"learn":[0.4422568306],"iteration":49,"passed_time":0.07720283917,"remaining_time":0.463217035},
{"learn":[0.4409025831],"iteration":50,"passed_time":0.07875705483,"remaining_time":0.4617325371},
{"learn":[0.4392063294],"iteration":51,"passed_time":0.08027953065,"remaining_time":0.4600634641},
{"learn":[0.4369152021],"iteration":52,"passed_time":0.08175821557,"remaining_time":0.4581545288},
{"learn":[0.4353188132],"iteration":53,"passed_time":0.08319974314,"remaining_time":0.4560578513},
{"learn":[0.4336374412],"iteration":54,"passed_time":0.08462068339,"remaining_time":0.4538745745},
{"learn":[0.4320569581],"iteration":55,"passed_time":0.08608164681,"remaining_time":0.4519286458},
{"learn":[0.4307611217],"iteration":56,"passed_time":0.0875576207,"remaining_time":0.4500768924},
{"learn":[0.4301602078],"iteration":57,"passed_time":0.08880147848,"remaining_time":0.4470695123},
{"learn":[0.4286319766],"iteration":58,"passed_time":0.09035867917,"remaining_time":0.4456673837},
{"learn":[0.4270430501],"iteration":59,"passed_time":0.09204312436,"remaining_time":0.4448751011},
{"learn":[0.4259146734],"iteration":60,"passed_time":0.09350763739,"remaining_time":0.4430115935},
{"learn":[0.4246666774],"iteration":61,"passed_time":0.09491406758,"remaining_time":0.4408911526},
{"learn":[0.4237553571],"iteration":62,"passed_time":0.09633526071,"remaining_time":0.4388606321},
{"learn":[0.4223483253],"iteration":63,"passed_time":0.09814408704,"remaining_time":0.438581389},
{"learn":[0.421058388],"iteration":64,"passed_time":0.1003641152,"remaining_time":0.4400580436},
{"learn":[0.4197048229],"iteration":65,"passed_time":0.101848454,"remaining_time":0.4382569838},
{"learn":[0.4186720948],"iteration":66,"passed_time":0.1033361768,"remaining_time":0.4364796722},
{"learn":[0.4177468863],"iteration":67,"passed_time":0.1048418272,"remaining_time":0.4347852247},
{"learn":[0.4167088664],"iteration":68,"passed_time":0.1068475812,"remaining_time":0.4351329033},
{"learn":[0.4152229865],"iteration":69,"passed_time":0.1086011086,"remaining_time":0.4344044344},
{"learn":[0.4140758453],"iteration":70,"passed_time":0.1101745221,"remaining_time":0.4329393194},
{"learn":[0.4128351584],"iteration":71,"passed_time":0.1115986717,"remaining_time":0.4308948715},
{"learn":[0.4117859981],"iteration":72,"passed_time":0.1132940062,"remaining_time":0.4298964345},
{"learn":[0.4109117433],"iteration":73,"passed_time":0.1149675195,"remaining_time":0.4287977754},
{"learn":[0.4102686086],"iteration":74,"passed_time":0.1163336484,"remaining_time":0.4265567107},
{"learn":[0.4090655833],"iteration":75,"passed_time":0.1178352198,"remaining_time":0.4248269767},
{"learn":[0.4081744389],"iteration":76,"passed_time":0.1194351734,"remaining_time":0.4234519783},
{"learn":[0.4075549708],"iteration":77,"passed_time":0.1209843531,"remaining_time":0.4218941544},
{"learn":[0.4063107457],"iteration":78,"passed_time":0.1228663,"remaining_time":0.4214780672},
{"learn":[0.4060201477],"iteration":79,"passed_time":0.1242104935,"remaining_time":0.4192104156},
{"learn":[0.4055841973],"iteration":80,"passed_time":0.125777444,"remaining_time":0.4177053387},
{"learn":[0.4047457091],"iteration":81,"passed_time":0.1273736232,"remaining_time":0.4162942807},
{"learn":[0.4045573171],"iteration":82,"passed_time":0.1285750166,"remaining_time":0.4136087884},
{"learn":[0.4037430615],"iteration":83,"passed_time":0.1300912786,"remaining_time":0.4119557155},
{"learn":[0.4030104429],"iteration":84,"passed_time":0.1315870906,"remaining_time":0.4102421061},
{"learn":[0.4019713828],"iteration":85,"passed_time":0.1330896178,"remaining_time":0.4085541755},
{"learn":[0.4008985686],"iteration":86,"passed_time":0.1346041877,"remaining_time":0.4069069123},
{"learn":[0.4001053556],"iteration":87,"passed_time":0.1361318613,"remaining_time":0.405301678},
{"learn":[0.3993181646],"iteration":88,"passed_time":0.1376651978,"remaining_time":0.4037147936},
{"learn":[0.3987805978],"iteration":89,"passed_time":0.1393520109,"remaining_time":0.402572476},
{"learn":[0.3981739965],"iteration":90,"passed_time":0.1409286268,"remaining_time":0.4011045532},
{"learn":[0.3976533048],"iteration":91,"passed_time":0.1423875141,"remaining_time":0.3993041157},
{"learn":[0.3968870906],"iteration":92,"passed_time":0.1441036312,"remaining_time":0.3982218627},
{"learn":[0.3967948729],"iteration":93,"passed_time":0.1453090064,"remaining_time":0.3957351663},
{"learn":[0.3962333748],"iteration":94,"passed_time":0.1469137686,"remaining_time":0.3943474841},
{"learn":[0.3952623574],"iteration":95,"passed_time":0.1485021334,"remaining_time":0.3929118946},
{"learn":[0.3946215354],"iteration":96,"passed_time":0.1500851912,"remaining_time":0.391459313},
{"learn":[0.3938278946],"iteration":97,"passed_time":0.1516186784,"remaining_time":0.3898766015},
{"learn":[0.393562173],"iteration":98,"passed_time":0.1536544495,"remaining_time":0.3895683519},
{"learn":[0.3934076283],"iteration":99,"passed_time":0.1549947255,"remaining_time":0.3874868136},
{"learn":[0.3930067719],"iteration":100,"passed_time":0.1565320429,"remaining_time":0.3859057294},
{"learn":[0.3925575665],"iteration":101,"passed_time":0.1580798162,"remaining_time":0.3843509256},
{"learn":[0.3921411957],"iteration":102,"passed_time":0.1596252721,"remaining_time":0.382790701},
{"learn":[0.3916059653],"iteration":103,"passed_time":0.1612004612,"remaining_time":0.381301091},
{"learn":[0.390890396],"iteration":104,"passed_time":0.162753412,"remaining_time":0.3797579614},
{"learn":[0.3905561823],"iteration":105,"passed_time":0.1643024304,"remaining_time":0.3782055944},
{"learn":[0.3899554709],"iteration":106,"passed_time":0.1657703398,"remaining_time":0.3764690895},
{"learn":[0.3897922803],"iteration":107,"passed_time":0.1670944364,"remaining_time":0.3744153113},
{"learn":[0.3894409804],"iteration":108,"passed_time":0.1686231626,"remaining_time":0.3728273594},
{"learn":[0.3891754274],"iteration":109,"passed_time":0.1701782321,"remaining_time":0.3712979609},
{"learn":[0.3885188991],"iteration":110,"passed_time":0.1721422084,"remaining_time":0.3706485388},
{"learn":[0.387916992],"iteration":111,"passed_time":0.1737634765,"remaining_time":0.3692473875},
{"learn":[0.3872548378],"iteration":112,"passed_time":0.1752135966,"remaining_time":0.367483384},
{"learn":[0.3866657105],"iteration":113,"passed_time":0.1767093408,"remaining_time":0.365819337},
{"learn":[0.3866152402],"iteration":114,"passed_time":0.1778993457,"remaining_time":0.3635334457},
{"learn":[0.3859563769],"iteration":115,"passed_time":0.1794771516,"remaining_time":0.3620487368},
{"learn":[0.3854707853],"iteration":116,"passed_time":0.1810020599,"remaining_time":0.3604570936},
{"learn":[0.3849317871],"iteration":117,"passed_time":0.1825622477,"remaining_time":0.3589359446},
{"learn":[0.3844286686],"iteration":118,"passed_time":0.1841236379,"remaining_time":0.3574164735},
{"learn":[0.383909273],"iteration":119,"passed_time":0.185934107,"remaining_time":0.356373705},
{"learn":[0.3835439885],"iteration":120,"passed_time":0.1874909666,"remaining_time":0.3548382756},
{"learn":[0.3828817007],"iteration":121,"passed_time":0.1889880067,"remaining_time":0.353190701},
{"learn":[0.3823938074],"iteration":122,"passed_time":0.1903610642,"remaining_time":0.3513167608},
{"learn":[0.3818173791],"iteration":123,"passed_time":0.1917395848,"remaining_time":0.3494608562},
{"learn":[0.3813536948],"iteration":124,"passed_time":0.1931367503,"remaining_time":0.3476461505},
{"learn":[0.3809326458],"iteration":125,"passed_time":0.1945944062,"remaining_time":0.3459456111},
{"learn":[0.3808319997],"iteration":126,"passed_time":0.1959777529,"remaining_time":0.3441184165},
{"learn":[0.3804753219],"iteration":127,"passed_time":0.1973673482,"remaining_time":0.3423089945},
{"learn":[0.3802266669],"iteration":128,"passed_time":0.1988075426,"remaining_time":0.3405927667},
{"learn":[0.3797929745],"iteration":129,"passed_time":0.2002257552,"remaining_time":0.3388435857},
{"learn":[0.3792004781],"iteration":130,"passed_time":0.2017916763,"remaining_time":0.3373463902},
{"learn":[0.3791237917],"iteration":131,"passed_time":0.2031865236,"remaining_time":0.3355656223},
{"learn":[0.3784429956],"iteration":132,"passed_time":0.204817046,"remaining_time":0.3341751804},
{"learn":[0.3780144768],"iteration":133,"passed_time":0.2062727894,"remaining_time":0.3324994217},
{"learn":[0.3778932011],"iteration":134,"passed_time":0.2076362573,"remaining_time":0.3306799653},
{"learn":[0.3773408223],"iteration":135,"passed_time":0.2090415356,"remaining_time":0.3289330045},
{"learn":[0.3768382642],"iteration":136,"passed_time":0.2104038574,"remaining_time":0.3271242455},
{"learn":[0.3766721247],"iteration":137,"passed_time":0.2117953757,"remaining_time":0.325366809},
{"learn":[0.3765531378],"iteration":138,"passed_time":0.2131837392,"remaining_time":0.3236098487},
{"learn":[0.3763583088],"iteration":139,"passed_time":0.2145288966,"remaining_time":0.3217933449},
{"learn":[0.3759977302],"iteration":140,"passed_time":0.2160079284,"remaining_time":0.3201819648},
{"learn":[0.3752711676],"iteration":141,"passed_time":0.2175602583,"remaining_time":0.318679815},
{"learn":[0.3749987029],"iteration":142,"passed_time":0.218996841,"remaining_time":0.3170094132},
{"learn":[0.3746408561],"iteration":143,"passed_time":0.2204217063,"remaining_time":0.3153254965},
{"learn":[0.3742146839],"iteration":144,"passed_time":0.2221285111,"remaining_time":0.3140437571},
{"learn":[0.37374457],"iteration":145,"passed_time":0.2235965762,"remaining_time":0.3124226133},
{"learn":[0.3733503002],"iteration":146,"passed_time":0.225039261,"remaining_time":0.3107685033},
{"learn":[0.3731195364],"iteration":147,"passed_time":0.2264647649,"remaining_time":0.3090938008},
{"learn":[0.3726394141],"iteration":148,"passed_time":0.2278850827,"remaining_time":0.3074154471},
{"learn":[0.3722743763],"iteration":149,"passed_time":0.2293258507,"remaining_time":0.305767801},
{"learn":[0.372090871],"iteration":150,"passed_time":0.2310102165,"remaining_time":0.3044439276},
{"learn":[0.3716584486],"iteration":151,"passed_time":0.2327620324,"remaining_time":0.3032031737},
{"learn":[0.3713043548],"iteration":152,"passed_time":0.234670588,"remaining_time":0.3021575545},
{"learn":[0.370992724],"iteration":153,"passed_time":0.2361289066,"remaining_time":0.3005276994},
{"learn":[0.3707998458],"iteration":154,"passed_time":0.2375656653,"remaining_time":0.2988729337},
{"learn":[0.3704153268],"iteration":155,"passed_time":0.2392127201,"remaining_time":0.2974824852},
{"learn":[0.370141459],"iteration":156,"passed_time":0.2410114849,"remaining_time":0.2962752649},
{"learn":[0.3697049101],"iteration":157,"passed_time":0.2424066335,"remaining_time":0.2945700863},
{"learn":[0.3694232316],"iteration":158,"passed_time":0.2438112467,"remaining_time":0.2928801768},
{"learn":[0.3691295899],"iteration":159,"passed_time":0.2452374513,"remaining_time":0.2912194734},
{"learn":[0.3688748108],"iteration":160,"passed_time":0.2466690863,"remaining_time":0.2895680578},
{"learn":[0.3685669258],"iteration":161,"passed_time":0.248103705,"remaining_time":0.2879228182},
{"learn":[0.3685375694],"iteration":162,"passed_time":0.2494719543,"remaining_time":0.2862040212},
{"learn":[0.3682047744],"iteration":163,"passed_time":0.2508588965,"remaining_time":0.2845106997},
{"learn":[0.3676811893],"iteration":164,"passed_time":0.2523106627,"remaining_time":0.2828937733},
{"learn":[0.3675214557],"iteration":165,"passed_time":0.2539414997,"remaining_time":0.281477325},
{"learn":[0.36726243],"iteration":166,"passed_time":0.2553874311,"remaining_time":0.279855688},
{"learn":[0.3670841068],"iteration":167,"passed_time":0.2568262468,"remaining_time":0.2782284341},
{"learn":[0.3667798147],"iteration":168,"passed_time":0.2582733898,"remaining_time":0.2766123287},
{"learn":[0.3667026612],"iteration":169,"passed_time":0.2596412545,"remaining_time":0.2749142695},
{"learn":[0.3664448194],"iteration":170,"passed_time":0.2611100117,"remaining_time":0.2733256847},
{"learn":[0.3659582539],"iteration":171,"passed_time":0.2625511175,"remaining_time":0.2717098774},
{"learn":[0.3656349795],"iteration":172,"passed_time":0.2642783875,"remaining_time":0.2703888705},
{"learn":[0.3654123371],"iteration":173,"passed_time":0.2658753755,"remaining_time":0.2689314143},
{"learn":[0.3651901483],"iteration":174,"passed_time":0.2675133887,"remaining_time":0.2675133887},
{"learn":[0.3650375373],"iteration":175,"passed_time":0.2688441035,"remaining_time":0.2657890569},
{"learn":[0.3647952388],"iteration":176,"passed_time":0.270294126,"remaining_time":0.2641857841},
{"learn":[0.3647126516],"iteration":177,"passed_time":0.2717253313,"remaining_time":0.2625660505},
{"learn":[0.3644387435],"iteration":178,"passed_time":0.2734741812,"remaining_time":0.2612518715},
{"learn":[0.3641803268],"iteration":179,"passed_time":0.2752540057,"remaining_time":0.2599621165},
{"learn":[0.3638884821],"iteration":180,"passed_time":0.2770936791,"remaining_time":0.2587228274},
{"learn":[0.3636062873],"iteration":181,"passed_time":0.2789577261,"remaining_time":0.2574994395},
{"learn":[0.3632825551],"iteration":182,"passed_time":0.2809489423,"remaining_time":0.2563851004},
{"learn":[0.3629873341],"iteration":183,"passed_time":0.2828143884,"remaining_time":0.2551477634},
{"learn":[0.3628664167],"iteration":184,"passed_time":0.2848761896,"remaining_time":0.2540787637},
{"learn":[0.3625219202],"iteration":185,"passed_time":0.2864370153,"remaining_time":0.2525573683},
{"learn":[0.3624486678],"iteration":186,"passed_time":0.287785534,"remaining_time":0.2508504922},
{"learn":[0.3624340459],"iteration":187,"passed_time":0.2891598171,"remaining_time":0.2491696296},
{"learn":[0.3623524466],"iteration":188,"passed_time":0.2906876202,"remaining_time":0.2476227876},
{"learn":[0.3620762602],"iteration":189,"passed_time":0.2922947578,"remaining_time":0.2461429539},
{"learn":[0.3617973224],"iteration":190,"passed_time":0.293787283,"remaining_time":0.244566377},
{"learn":[0.3614411263],"iteration":191,"passed_time":0.296082421,"remaining_time":0.243651159},
{"learn":[0.3611553176],"iteration":192,"passed_time":0.297785408,"remaining_time":0.2422399433},
{"learn":[0.3611331668],"iteration":193,"passed_time":0.2990414887,"remaining_time":0.2404663517},
{"learn":[0.3609069599],"iteration":194,"passed_time":0.3005416893,"remaining_time":0.238892112},
{"learn":[0.360788826],"iteration":195,"passed_time":0.3020078231,"remaining_time":0.237291861},
{"learn":[0.3607403353],"iteration":196,"passed_time":0.3034076065,"remaining_time":0.2356414406},
{"learn":[0.3604989943],"iteration":197,"passed_time":0.304954663,"remaining_time":0.23410661},
{"learn":[0.3603653413],"iteration":198,"passed_time":0.3064956215,"remaining_time":0.2325670293},
{"learn":[0.3601401032],"iteration":199,"passed_time":0.3082713197,"remaining_time":0.2312034898},
{"learn":[0.3598607716],"iteration":200,"passed_time":0.3098815761,"remaining_time":0.2297132081},
{"learn":[0.3597648137],"iteration":201,"passed_time":0.3117912468,"remaining_time":0.2284411115},
{"learn":[0.3595586278],"iteration":202,"passed_time":0.3132918857,"remaining_time":0.2268665379},
{"learn":[0.3594262449],"iteration":203,"passed_time":0.3149635468,"remaining_time":0.2254150874},
{"learn":[0.3592104248],"iteration":204,"passed_time":0.3165046878,"remaining_time":0.2238691694},
{"learn":[0.3591682625],"iteration":205,"passed_time":0.3180046471,"remaining_time":0.2222945106},
{"learn":[0.3587371171],"iteration":206,"passed_time":0.3195132118,"remaining_time":0.2207265183},
{"learn":[0.3584685657],"iteration":207,"passed_time":0.3210192323,"remaining_time":0.2191573605},
{"learn":[0.3580086831],"iteration":208,"passed_time":0.3225120411,"remaining_time":0.2175798937},
{"learn":[0.3576907155],"iteration":209,"passed_time":0.3240394613,"remaining_time":0.2160263075},
{"learn":[0.3575231819],"iteration":210,"passed_time":0.3255745756,"remaining_time":0.2144780379},
{"learn":[0.3572751648],"iteration":211,"passed_time":0.3271685027,"remaining_time":0.2129681763},
{"learn":[0.357158413],"iteration":212,"passed_time":0.3289441224,"remaining_time":0.2115743886},
{"learn":[0.3569555759],"iteration":213,"passed_time":0.3307727264,"remaining_time":0.2102107047},
{"learn":[0.3566391758],"iteration":214,"passed_time":0.3322735202,"remaining_time":0.2086368615},
{"learn":[0.3563883913],"iteration":215,"passed_time":0.3338245252,"remaining_time":0.2070948444},
{"learn":[0.3562702804],"iteration":216,"passed_time":0.3352765857,"remaining_time":0.2054921009},
{"learn":[0.356008273],"iteration":217,"passed_time":0.3368102302,"remaining_time":0.2039401394},
{"learn":[0.3559345932],"iteration":218,"passed_time":0.3383439827,"remaining_time":0.2023884097},
{"learn":[0.3558037432],"iteration":219,"passed_time":0.3398390865,"remaining_time":0.2008140057},
{"learn":[0.3555898843],"iteration":220,"passed_time":0.3414812673,"remaining_time":0.1993261696},
{"learn":[0.355395276],"iteration":221,"passed_time":0.3431074127,"remaining_time":0.1978276974},
{"learn":[0.3553331297],"iteration":222,"passed_time":0.3447947337,"remaining_time":0.1963629201},
{"learn":[0.3551628348],"iteration":223,"passed_time":0.3465486584,"remaining_time":0.1949336204},
{"learn":[0.3551523236],"iteration":224,"passed_time":0.3479489857,"remaining_time":0.193304992},
{"learn":[0.3550301703],"iteration":225,"passed_time":0.3494333729,"remaining_time":0.1917245055},
{"learn":[0.3547780079],"iteration":226,"passed_time":0.3509779538,"remaining_time":0.1901774816},
{"learn":[0.3545515927],"iteration":227,"passed_time":0.3525424619,"remaining_time":0.1886411419},
{"learn":[0.3543327427],"iteration":228,"passed_time":0.3541741871,"remaining_time":0.1871400727},
{"learn":[0.3539852048],"iteration":229,"passed_time":0.3557217688,"remaining_time":0.1855939663},
{"learn":[0.3538581794],"iteration":230,"passed_time":0.357259611,"remaining_time":0.1840428299},
{"learn":[0.3536425571],"iteration":231,"passed_time":0.359124786,"remaining_time":0.1826582963},
{"learn":[0.3534107879],"iteration":232,"passed_time":0.3608732087,"remaining_time":0.1812110104},
{"learn":[0.353240386],"iteration":233,"passed_time":0.362472676,"remaining_time":0.1796873094},
{"learn":[0.3528754003],"iteration":234,"passed_time":0.3640055526,"remaining_time":0.1781303768},
{"learn":[0.3528457103],"iteration":235,"passed_time":0.3655053907,"remaining_time":0.1765576887},
{"learn":[0.3527430716],"iteration":236,"passed_time":0.3670005947,"remaining_time":0.1749834059},
{"learn":[0.3524939072],"iteration":237,"passed_time":0.3684800019,"remaining_time":0.1734023538},
{"learn":[0.3522985581],"iteration":238,"passed_time":0.3699497897,"remaining_time":0.1718176847},
{"learn":[0.3521045048],"iteration":239,"passed_time":0.3714407711,"remaining_time":0.1702436867},
{"learn":[0.3519918197],"iteration":240,"passed_time":0.3732927166,"remaining_time":0.1688336353},
{"learn":[0.3519634731],"iteration":241,"passed_time":0.3748334904,"remaining_time":0.1672810619},
{"learn":[0.3519572066],"iteration":242,"passed_time":0.3762696762,"remaining_time":0.1656825323},
{"learn":[0.3519554108],"iteration":243,"passed_time":0.3774632706,"remaining_time":0.1639799454},
{"learn":[0.3519191371],"iteration":244,"passed_time":0.3791717355,"remaining_time":0.1625021724},
{"learn":[0.3518933316],"iteration":245,"passed_time":0.3806234574,"remaining_time":0.160913982},
{"learn":[0.351792322],"iteration":246,"passed_time":0.3823397414,"remaining_time":0.1594372201},
{"learn":[0.3516764187],"iteration":247,"passed_time":0.3838987785,"remaining_time":0.1578938525},
{"learn":[0.3515419058],"iteration":248,"passed_time":0.3854845573,"remaining_time":0.156361206},
{"learn":[0.3512013206],"iteration":249,"passed_time":0.3870305964,"remaining_time":0.1548122386},
{"learn":[0.3509431033],"iteration":250,"passed_time":0.3885368759,"remaining_time":0.1532476124},
{"learn":[0.3506959046],"iteration":251,"passed_time":0.3900529309,"remaining_time":0.1516872509},
{"learn":[0.3504849333],"iteration":252,"passed_time":0.3920894997,"remaining_time":0.1503268042},
{"learn":[0.3502747179],"iteration":253,"passed_time":0.3936126485,"remaining_time":0.1487669853},
{"learn":[0.3502260525],"iteration":254,"passed_time":0.3950622802,"remaining_time":0.1471800652},
{"learn":[0.350096223],"iteration":255,"passed_time":0.3965276252,"remaining_time":0.1455999874},
{"learn":[0.3498487772],"iteration":256,"passed_time":0.398116033,"remaining_time":0.1440653349},
{"learn":[0.3496639195],"iteration":257,"passed_time":0.3996672964,"remaining_time":0.1425170204},
{"learn":[0.3496433343],"iteration":258,"passed_time":0.4009595873,"remaining_time":0.1408776928},
{"learn":[0.3494578284],"iteration":259,"passed_time":0.4025165202,"remaining_time":0.1393326416},
{"learn":[0.3492232451],"iteration":260,"passed_time":0.4040654864,"remaining_time":0.1377847827},
{"learn":[0.3488547162],"iteration":261,"passed_time":0.4059579476,"remaining_time":0.1363522877},
{"learn":[0.3485832025],"iteration":262,"passed_time":0.4074490731,"remaining_time":0.1347835337},
{"learn":[0.3485319273],"iteration":263,"passed_time":0.4089661277,"remaining_time":0.1332238143},
{"learn":[0.3482025958],"iteration":264,"passed_time":0.4104441756,"remaining_time":0.1316519054},
{"learn":[0.3479777713],"iteration":265,"passed_time":0.4119195547,"remaining_time":0.1300798594},
{"learn":[0.3479200892],"iteration":266,"passed_time":0.4134121748,"remaining_time":0.128513897},
{"learn":[0.3477926021],"iteration":267,"passed_time":0.4149434609,"remaining_time":0.1269603127},
{"learn":[0.3476133386],"iteration":268,"passed_time":0.416466327,"remaining_time":0.1254043587},
{"learn":[0.3474539649],"iteration":269,"passed_time":0.4180093616,"remaining_time":0.1238546257},
{"learn":[0.3473342499],"iteration":270,"passed_time":0.4195093731,"remaining_time":0.1222924003},
{"learn":[0.3470869029],"iteration":271,"passed_time":0.4209835316,"remaining_time":0.1207232186},
{"learn":[0.3468357779],"iteration":272,"passed_time":0.4226771181,"remaining_time":0.1192166231},
{"learn":[0.3467555132],"iteration":273,"passed_time":0.4243910996,"remaining_time":0.1177143196},
{"learn":[0.3466263414],"iteration":274,"passed_time":0.4259044638,"remaining_time":0.1161557629},
{"learn":[0.3463493526],"iteration":275,"passed_time":0.4274025093,"remaining_time":0.1145934264},
{"learn":[0.3461463159],"iteration":276,"passed_time":0.4289366392,"remaining_time":0.1130410638},
{"learn":[0.3460148702],"iteration":277,"passed_time":0.4304593096,"remaining_time":0.1114858644},
{"learn":[0.3457304199],"iteration":278,"passed_time":0.4322382603,"remaining_time":0.1099961164},
{"learn":[0.3455765345],"iteration":279,"passed_time":0.4338123634,"remaining_time":0.1084530908},
{"learn":[0.3453780612],"iteration":280,"passed_time":0.4354897508,"remaining_time":0.1069352057},
{"learn":[0.3451547935],"iteration":281,"passed_time":0.4370477668,"remaining_time":0.1053874048},
{"learn":[0.3451148109],"iteration":282,"passed_time":0.438540778,"remaining_time":0.1038241418},
{"learn":[0.3449741128],"iteration":283,"passed_time":0.440019018,"remaining_time":0.1022579408},
{"learn":[0.3448717776],"iteration":284,"passed_time":0.4415664768,"remaining_time":0.1007081438},
{"learn":[0.3447903833],"iteration":285,"passed_time":0.4430968651,"remaining_time":0.09915454324},
{"learn":[0.3445473718],"iteration":286,"passed_time":0.4446267385,"remaining_time":0.09760099139},
{"learn":[0.3444289293],"iteration":287,"passed_time":0.4461267413,"remaining_time":0.09604117348},
{"learn":[0.3443951262],"iteration":288,"passed_time":0.4474668695,"remaining_time":0.09444802435},
{"learn":[0.3442996842],"iteration":289,"passed_time":0.4489283702,"remaining_time":0.09288173176},
{"learn":[0.3441549796],"iteration":290,"passed_time":0.450405839,"remaining_time":0.09131939692},
{"learn":[0.3439466724],"iteration":291,"passed_time":0.4519090156,"remaining_time":0.08976274967},
{"learn":[0.3438578505],"iteration":292,"passed_time":0.4534633053,"remaining_time":0.08821641094},
{"learn":[0.3436968909],"iteration":293,"passed_time":0.4550963352,"remaining_time":0.08668501623},
{"learn":[0.3432950494],"iteration":294,"passed_time":0.4566241582,"remaining_time":0.08513331763},
{"learn":[0.3431443117],"iteration":295,"passed_time":0.4580760688,"remaining_time":0.08356793147},
{"learn":[0.3429254106],"iteration":296,"passed_time":0.4597357802,"remaining_time":0.08204039176},
{"learn":[0.3427318991],"iteration":297,"passed_time":0.4612416434,"remaining_time":0.08048511898},
{"learn":[0.3425913545],"iteration":298,"passed_time":0.4627801826,"remaining_time":0.07893575022},
{"learn":[0.3424705294],"iteration":299,"passed_time":0.4643180327,"remaining_time":0.07738633879},
{"learn":[0.3424228192],"iteration":300,"passed_time":0.4658004278,"remaining_time":0.07582797663},
{"learn":[0.3423799097],"iteration":301,"passed_time":0.4673472492,"remaining_time":0.07428035749},
{"learn":[0.3421001732],"iteration":302,"passed_time":0.4692165623,"remaining_time":0.07278276709},
{"learn":[0.3420157839],"iteration":303,"passed_time":0.4707378043,"remaining_time":0.07123006249},
{"learn":[0.342015213],"iteration":304,"passed_time":0.4719022088,"remaining_time":0.06962491605},
{"learn":[0.3418198575],"iteration":305,"passed_time":0.4734233722,"remaining_time":0.06807394894},
{"learn":[0.3416681666],"iteration":306,"passed_time":0.4749816776,"remaining_time":0.06652837829},
{"learn":[0.341464683],"iteration":307,"passed_time":0.4765223368,"remaining_time":0.06498031865},
{"learn":[0.3413240744],"iteration":308,"passed_time":0.4779798818,"remaining_time":0.06342127882},
{"learn":[0.341172569],"iteration":309,"passed_time":0.4794704812,"remaining_time":0.06186715887},
{"learn":[0.3410438964],"iteration":310,"passed_time":0.481259159,"remaining_time":0.06035082701},
{"learn":[0.3410179405],"iteration":311,"passed_time":0.4828786527,"remaining_time":0.05881214359},
{"learn":[0.3407910002],"iteration":312,"passed_time":0.4845674902,"remaining_time":0.05728114101},
{"learn":[0.3406503017],"iteration":313,"passed_time":0.4862390763,"remaining_time":0.05574715525},
{"learn":[0.340524573],"iteration":314,"passed_time":0.4879729042,"remaining_time":0.05421921158},
{"learn":[0.340368411],"iteration":315,"passed_time":0.4895985708,"remaining_time":0.05267832724},
{"learn":[0.3402640994],"iteration":316,"passed_time":0.4912213041,"remaining_time":0.05113660263},
{"learn":[0.3399173966],"iteration":317,"passed_time":0.4927023582,"remaining_time":0.04958011151},
{"learn":[0.3398432614],"iteration":318,"passed_time":0.4944127337,"remaining_time":0.04804637851},
{"learn":[0.3397470094],"iteration":319,"passed_time":0.4959211606,"remaining_time":0.0464926088},
{"learn":[0.3395400033],"iteration":320,"passed_time":0.4974519255,"remaining_time":0.04494113969},
{"learn":[0.3393956642],"iteration":321,"passed_time":0.4990123323,"remaining_time":0.04339237672},
{"learn":[0.3392452289],"iteration":322,"passed_time":0.500859652,"remaining_time":0.04186752509},
{"learn":[0.3391852263],"iteration":323,"passed_time":0.5024244192,"remaining_time":0.04031800895},
{"learn":[0.3390418361],"iteration":324,"passed_time":0.5040148506,"remaining_time":0.03877037312},
{"learn":[0.3389291198],"iteration":325,"passed_time":0.5055882683,"remaining_time":0.0372212222},
{"learn":[0.3389244174],"iteration":326,"passed_time":0.5067973428,"remaining_time":0.03564629628},
{"learn":[0.3387959242],"iteration":327,"passed_time":0.5083255785,"remaining_time":0.03409500831},
{"learn":[0.338452839],"iteration":328,"passed_time":0.5098585475,"remaining_time":0.0325441626},
{"learn":[0.3382980488],"iteration":329,"passed_time":0.5114577605,"remaining_time":0.03099744003},
{"learn":[0.3379566174],"iteration":330,"passed_time":0.513087711,"remaining_time":0.02945216468},
{"learn":[0.3378135431],"iteration":331,"passed_time":0.5146304699,"remaining_time":0.02790165198},
{"learn":[0.3377052216],"iteration":332,"passed_time":0.5162526689,"remaining_time":0.02635524135},
{"learn":[0.337442766],"iteration":333,"passed_time":0.5182180847,"remaining_time":0.02482481843},
{"learn":[0.3374121167],"iteration":334,"passed_time":0.5197408213,"remaining_time":0.02327197707},
{"learn":[0.3372856017],"iteration":335,"passed_time":0.5214450359,"remaining_time":0.0217268765},
{"learn":[0.3372121988],"iteration":336,"passed_time":0.5230929844,"remaining_time":0.02017866112},
{"learn":[0.336855663],"iteration":337,"passed_time":0.5246549523,"remaining_time":0.01862680304},
{"learn":[0.3368205629],"iteration":338,"passed_time":0.5262063601,"remaining_time":0.01707454266},
{"learn":[0.3367481653],"iteration":339,"passed_time":0.5279353296,"remaining_time":0.01552750969},
{"learn":[0.3366010197],"iteration":340,"passed_time":0.5297715776,"remaining_time":0.01398224105},
{"learn":[0.3363769712],"iteration":341,"passed_time":0.5320599905,"remaining_time":0.01244584773},
{"learn":[0.3361454478],"iteration":342,"passed_time":0.533548965,"remaining_time":0.01088875439},
{"learn":[0.3360449578],"iteration":343,"passed_time":0.5349948145,"remaining_time":0.009331304903},
{"learn":[0.3359392352],"iteration":344,"passed_time":0.5364382137,"remaining_time":0.007774466865},
{"learn":[0.3357746355],"iteration":345,"passed_time":0.5379843215,"remaining_time":0.006219471925},
{"learn":[0.3357340519],"iteration":346,"passed_time":0.5394787089,"remaining_time":0.004664081057},
{"learn":[0.3355443316],"iteration":347,"passed_time":0.5409282177,"remaining_time":0.00310878286},
{"learn":[0.335416191],"iteration":348,"passed_time":0.5424102411,"remaining_time":0.001554184072},
{"learn":[0.3351729604],"iteration":349,"passed_time":0.5438708453,"remaining_time":0}
]}